mk/__init__.py
mk/__main__.py
mk/_typer.py
mk/_version.py
mk/ctx.py
mk/exec.py
mk/loaders.py
mk/pre.py
mk/runner.py
mk/text.py
mk/tools/__init__.py
mk/tools/ansible.py
mk/tools/cmake.py
mk/tools/git.py
mk/tools/make.py
mk/tools/node.py
mk/tools/nox.py
mk/tools/pre.py
mk/tools/pre_commit.py
mk/tools/py_package.py
mk/tools/pytest.py
mk/tools/shell.py
mk/tools/taskfile.py
mk/tools/tox.py
mk-3.0.0.dist-info/licenses/LICENSE
mk-3.0.0.dist-info/METADATA
mk-3.0.0.dist-info/WHEEL
mk-3.0.0.dist-info/entry_points.txt
mk-3.0.0.dist-info/top_level.txt
mk-3.0.0.dist-info/RECORD
