Metadata-Version: 2.4
Name: mk
Version: 3.0.0
Summary: mk
Author-email: Sorin Sbarnea <sorin.sbarnea@gmail.com>
Project-URL: changelog, https://github.com/pycontribs/mk/releases
Project-URL: documentation, https://mk.readthedocs.io/
Project-URL: homepage, https://github.com/pycontribs/mk
Project-URL: repository, https://github.com/pycontribs/mk
Keywords: mk
Classifier: Development Status :: 5 - Production/Stable
Classifier: Environment :: Console
Classifier: Intended Audience :: Developers
Classifier: Intended Audience :: Information Technology
Classifier: Intended Audience :: System Administrators
Classifier: License :: OSI Approved :: MIT License
Classifier: Operating System :: MacOS
Classifier: Operating System :: POSIX
Classifier: Programming Language :: Python :: 3
Classifier: Programming Language :: Python :: 3.10
Classifier: Programming Language :: Python :: 3.11
Classifier: Programming Language :: Python :: 3.12
Classifier: Programming Language :: Python :: 3.13
Classifier: Programming Language :: Python :: 3 :: Only
Classifier: Programming Language :: Python
Classifier: Topic :: Software Development :: Quality Assurance
Classifier: Topic :: Software Development :: Testing
Classifier: Topic :: Utilities
Requires-Python: >=3.10
License-File: LICENSE
Requires-Dist: build>=0.3.1.post1
Requires-Dist: diskcache>=5.2.1
Requires-Dist: gitpython>=3.1.26
Requires-Dist: packaging>=22
Requires-Dist: pip>=21.0.1
Requires-Dist: pluggy>=1.5.0
Requires-Dist: pyyaml>=5.1
Requires-Dist: rich>=10.11.0
Requires-Dist: setuptools
Requires-Dist: shellingham>=1.5.4
Requires-Dist: subprocess-tee>=0.4.1
Requires-Dist: tomli>=2.0.1; python_version < "3.11"
Requires-Dist: twine>=3.4.1
Requires-Dist: typer-config>=1.4.0
Requires-Dist: typer>=0.16.0
Provides-Extra: docs
Requires-Dist: cairosvg>=2.6.0; extra == "docs"
Requires-Dist: markdown-exec>=1.3.0; extra == "docs"
Requires-Dist: mkdocs-autorefs; extra == "docs"
Requires-Dist: mkdocs-gen-files>=0.4.0; extra == "docs"
Requires-Dist: mkdocs-htmlproofer-plugin>=0.10.2; extra == "docs"
Requires-Dist: mkdocs-material-extensions>=1.1.1; extra == "docs"
Requires-Dist: mkdocs-material>=9.0.13; extra == "docs"
Requires-Dist: mkdocs>=1.4.2; extra == "docs"
Requires-Dist: pillow>=9.4.0; extra == "docs"
Requires-Dist: pipdeptree>=2.4.0; extra == "docs"
Requires-Dist: pymdown-extensions>=9.9.2; extra == "docs"
Provides-Extra: test
Requires-Dist: coverage>=7.5.3; extra == "test"
Requires-Dist: pytest>=8.0.0; extra == "test"
Requires-Dist: pytest-benchmark>=4.0.0; extra == "test"
Requires-Dist: pytest-plus>=0.7.0; extra == "test"
Requires-Dist: tox>=4.2.4; extra == "test"
Dynamic: license-file
